{"gameSeed":3,"allBattle":2,"mapSize":"SMALL","mapSeed":3,"bgmSeed":3,"output0":["RandomFall","2 0\r\n","1 1\r\n","4 0\r\n","8 0\r\n","7 2\r\n","3 0\r\n","3 2\r\n","3 3\r\n","3 3\r\n","4 3\r\n","4 2\r\n","2 1\r\n","4 3\r\n","7 1\r\n","5 3\r\n","2 3\r\n","5 0\r\n","6 2\r\n","6 2\r\n","0 2\r\n","6 0\r\n","1 2\r\n","1 0\r\n","7 2\r\n","7 1\r\n","2 1\r\n","3 2\r\n","3 2\r\n","3 2\r\n","4 0\r\n","1 2\r\n","1 1\r\n","6 2\r\n","3 2\r\n","4 3\r\n","3 3\r\n","3 3\r\n","6 0\r\n","4 2\r\n","4 2\r\n","0 0\r\n","2 2\r\n","1 0\r\n","7 3\r\n","6 2\r\n","2 2\r\n","3 0\r\n","5 1\r\n","5 2\r\n","6 0\r\n","3 0\r\n","5 2\r\n","8 0\r\n","1 2\r\n","7 3\r\n","4 1\r\n","3 0\r\n","4 2\r\n","3 0\r\n","-1 2\r\n","6 2\r\n","0 0\r\n","6 0\r\n","2 1\r\n","0 1\r\n","2 0\r\n","7 0\r\n","4 2\r\n","7 1\r\n","7 3\r\n","5 0\r\n","0 3\r\n","-1 0\r\n","5 1\r\n","2 3\r\n","5 1\r\n","6 2\r\n","3 1\r\n","6 3\r\n","5 3\r\n","4 0\r\n","2 0\r\n","3 2\r\n","6 2\r\n","3 0\r\n","2 2\r\n","4 3\r\n","1 1\r\n","3 3\r\n","7 2\r\n","3 3\r\n","7 2\r\n","3 1\r\n","4 2\r\n","0 0\r\n","6 2\r\n","5 2\r\n","1 2\r\n","4 1\r\n","4 2\r\n","7 1\r\n","5 2\r\n","2 1\r\n","4 3\r\n","1 1\r\n","5 0\r\n","0 0\r\n","7 3\r\n","1 1\r\n","5 1\r\n","7 1\r\n","4 3\r\n","5 1\r\n","2 0\r\n","0 2\r\n","5 3\r\n","3 2\r\n","3 0\r\n","3 0\r\n","1 3\r\n","2 0\r\n","8 0\r\n","0 3\r\n","2 1\r\n","2 2\r\n","1 1\r\n","7 0\r\n","4 0\r\n","6 0\r\n","0 3\r\n","3 0\r\n","7 0\r\n","8 0\r\n","3 1\r\n","5 1\r\n","6 3\r\n","1 2\r\n","3 2\r\n","2 1\r\n","0 2\r\n","6 3\r\n","5 0\r\n","5 1\r\n","1 0\r\n","6 0\r\n","6 2\r\n","7 2\r\n","2 1\r\n","8 2\r\n","2 2\r\n","4 1\r\n","8 0\r\n","7 2\r\n","2 0\r\n","6 3\r\n","7 2\r\n","1 0\r\n","3 2\r\n","4 3\r\n","2 0\r\n","5 2\r\n","0 0\r\n","4 0\r\n","7 2\r\n","6 1\r\n","0 0\r\n","3 1\r\n","3 0\r\n","7 2\r\n","7 3\r\n","3 1\r\n","1 1\r\n","6 2\r\n","4 0\r\n","0 0\r\n","4 0\r\n","1 0\r\n","2 1\r\n","4 2\r\n","0 2\r\n","2 3\r\n","4 0\r\n","5 2\r\n","2 1\r\n","-1 0\r\n","4 0\r\n","1 3\r\n","0 2\r\n","3 0\r\n","5 3\r\n","7 2\r\n","1 0\r\n","5 3\r\n","1 1\r\n","0 0\r\n","2 0\r\n","0 2\r\n","6 0\r\n","5 2\r\n","5 3\r\n","0 0\r\n","3 2\r\n","5 1\r\n","5 2\r\n","5 0\r\n","-1 1\r\n","2 1\r\n","3 1\r\n","5 1\r\n","3 1\r\n","4 1\r\n","2 1\r\n","-1 1\r\n","1 3\r\n","7 1\r\n","1 2\r\n","7 2\r\n","0 1\r\n","1 2\r\n","1 0\r\n","3 0\r\n","3 1\r\n","4 3\r\n","5 0\r\n","2 3\r\n","6 2\r\n","5 3\r\n","0 0\r\n","3 2\r\n","5 3\r\n","5 3\r\n","3 0\r\n","6 1\r\n","1 3\r\n","4 3\r\n","5 1\r\n","4 0\r\n","5 2\r\n","5 2\r\n","1 3\r\n","7 1\r\n","1 3\r\n","2 3\r\n","3 0\r\n","0 2\r\n","4 1\r\n","-1 1\r\n","5 1\r\n","1 1\r\n","1 3\r\n","4 3\r\n","4 3\r\n","6 0\r\n","3 1\r\n","0 3\r\n","5 0\r\n","2 2\r\n","6 3\r\n","5 1\r\n","6 0\r\n","7 0\r\n","2 0\r\n","4 1\r\n","1 0\r\n","1 0\r\n","0 0\r\n","4 1\r\n","5 2\r\n","4 2\r\n","5 2\r\n","0 2\r\n","4 0\r\n","0 0\r\n","7 2\r\n","4 1\r\n","7 0\r\n","1 0\r\n","4 2\r\n","8 2\r\n","3 2\r\n","2 1\r\n","0 0\r\n","2 0\r\n","7 2\r\n","2 1\r\n","2 2\r\n","1 1\r\n","7 3\r\n","0 3\r\n","6 0\r\n"],"output1":["SampleAI.cpp","-1 0\n","1 0\n","4 0\n","1 0\n","7 0\n","2 0\n","3 0\n","4 0\n","7 0\n","5 0\n","6 0\n","6 0\n","0 0\n","0 0\n","2 0\n","1 0\n","3 0\n","7 0\n","6 0\n","6 0\n","6 0\n","3 0\n","2 0\n","3 0\n","3 0\n","2 0\n","7 0\n","4 0\n","4 0\n","3 0\n","-1 0\n","4 0\n","3 0\n","0 0\n","0 0\n","-1 0\n","1 0\n","1 0\n","2 0\n","0 0\n","7 0\n","0 0\n","0 0\n","2 0\n","4 0\n","2 0\n","4 0\n","6 0\n","5 0\n","6 0\n","5 0\n","5 0\n","7 0\n","7 0\n","2 0\n","0 0\n","1 0\n","3 0\n","3 0\n","2 0\n","2 0\n","1 0\n","2 0\n","2 0\n","2 0\n","3 0\n","7 0\n","2 0\n","0 0\n","1 0\n","2 0\n","2 0\n","2 0\n","3 0\n","3 0\n","5 0\n","5 0\n","5 0\n","4 0\n","1 0\n","3 0\n","3 0\n","3 0\n","5 0\n","6 0\n","2 0\n","0 0\n","3 0\n","6 0\n","5 0\n","2 0\n","5 0\n","4 0\n","4 0\n","4 0\n","3 0\n","0 0\n","6 0\n","0 0\n","0 0\n","0 0\n","0 0\n","3 0\n","3 0\n","5 0\n","0 0\n","0 0\n","3 0\n","3 0\n","3 0\n","3 0\n","3 0\n","3 0\n","3 0\n","1 0\n","1 0\n","1 0\n","2 0\n","3 0\n","6 0\n","4 0\n","3 0\n","3 0\n","3 0\n","0 0\n","1 0\n","3 0\n","6 0\n","5 0\n","5 0\n","7 0\n","7 0\n","8 0\n","0 0\n","0 0\n","2 0\n","0 0\n","3 0\n","2 0\n","2 0\n","6 0\n","4 0\n","7 0\n","0 0\n","3 0\n","5 0\n","0 0\n","0 0\n","0 0\n","0 0\n","2 0\n","2 0\n","1 0\n","3 0\n","2 0\n","0 0\n","1 0\n","1 0\n","3 0\n","1 0\n","1 0\n","3 0\n","3 0\n","3 0\n","1 0\n","2 0\n","3 0\n","3 0\n","3 0\n","3 0\n","4 0\n","5 0\n","1 0\n","1 0\n","1 0\n","2 0\n","4 0\n","3 0\n","7 0\n","8 0\n","6 0\n","0 0\n","7 0\n","3 0\n","2 0\n","2 0\n","1 0\n","1 0\n","2 0\n","1 0\n","1 0\n","2 0\n","2 0\n","3 0\n","0 0\n","0 0\n","6 0\n","7 0\n","7 0\n","4 0\n","4 0\n","3 0\n","4 0\n","1 0\n","3 0\n","4 0\n","4 0\n","6 0\n","6 0\n","6 0\n","6 0\n","4 0\n","4 0\n","7 0\n","8 0\n","7 0\n","7 0\n","7 0\n","3 0\n","3 0\n","4 0\n","6 0\n","6 0\n","6 0\n","3 0\n","7 0\n","4 0\n","4 0\n","4 0\n","0 0\n","2 0\n","2 0\n","2 0\n","6 0\n","0 0\n","1 0\n","5 0\n","6 0\n","5 0\n","1 0\n","7 0\n","1 0\n","7 0\n","4 0\n","0 0\n","1 0\n","2 0\n","3 0\n","4 0\n","5 0\n","7 0\n","7 0\n","7 0\n","2 0\n","4 0\n","4 0\n","4 0\n","4 0\n","5 0\n","5 0\n","6 0\n","5 0\n","8 0\n","1 0\n","4 0\n","6 0\n","0 0\n","0 0\n","3 0\n","0 0\n","4 0\n","4 0\n","6 0\n","6 0\n","7 0\n","6 0\n","7 0\n","8 0\n","-1 0\n","3 0\n","6 0\n","5 0\n","4 0\n","4 0\n","3 0\n","1 0\n","1 0\n","1 0\n","-1 0\n","-1 0\n"],"thinkTime0":[3887505,2813626,1439359,1652794,1455003,1672140,1634565,2112559,2137772,1615498,1429721,2105435,2400934,1642318,2295543,2122966,1605930,1936140,2441372,2073308,2633436,2488095,1496559,1754762,2116610,1565912,1528616,1522959,1539092,2407569,1463035,1729550,2021835,2453804,1555366,1462127,2444724,2079943,1888997,2218438,1948013,1717048,1970082,2421118,1986286,2424680,2288140,2339683,2041949,2021765,2567924,2324597,1538254,1466248,1573593,1552432,2343803,1792407,2587969,2208731,1626743,1442362,1820762,1460521,1449695,2439136,1520863,1585188,2120102,1642807,1954508,1492648,2343175,2220254,1440616,1738559,1956813,2400445,2514146,2267188,2549067,2478457,1905619,1936280,1645880,2136584,2274871,2623797,2187359,2456179,1809308,1589657,2525879,1567029,2215714,2291562,2632667,1616616,2054312,2492425,2582032,1515137,2769626,1767543,2399327,2648661,1509130,2584267,1732203,2117518,2102852,2467632,1898496,2548718,1855403,1642388,1548520,2320686,2578610,1757695,1550476,1827467,1849747,1784933,4272889,2693498,1404718,1535111,1806514,2030286,2059759,2104178,1748686,1483359,1606419,1566610,1146375,1483010,1939982,1123606,1133664,1950038,1208464,1145467,1401016,1898146,1496140,1333479,1943333,1327543,1146514,1179549,1162858,1205809,1279562,1258121,1136318,1950877,1945428,1334318,1906528,1286965,1173403,1281028,1731086,1748407,2136305,1249391,1768381,1174032,1687645,1157829,1120394,1219708,1224876,1916514,2098870,1916305,2096984,1174870,1143372,1145257,1143231,1959467,1160901,1195543,1144977,2318940,1141765,1132476,1130242,1121512,1615708,1947664,1413098,1211537,1188000,1968546,1144628,1389423,1149169,1209860,1147003,1134921,1190444,1328102,1268527,1154826,1162438,1950667,1145676,2302946,1919238,1126470,1241848,1184368,1362953,1151822,1148680,1185974,1126819,1471974,1228927,1905549,1504032,1228717,1936698,1299885,1151124,1191632,1124515,1965193,1147143,1860990,1158876,1220127,1167816,1347867,1148261,1152800,1403880,2167594,1943333,2231778,1280400,1178222,1132197,1245550,1191981,1165093,1156641,1993689,1155175,1217753,1137714,1937328,1206718,1213562,1222571,1441035,1923778,1962051,1252533,1161460,1166280,1260007,1173403,1173124,1136527,1186534,1133454,1165720,1143093,1157130,1168934,1296673,1158806,1351080,1178362,1416591,1225784,1938444,1168724,1929016,1247784,2033498,2095448,1534064,1230184,1381111],"thinkTime1":[32517610,6970370,4995747,5479607,5347956,4866960,5410674,10324706,9995963,5176146,5184458,5046382,4965296,5751499,10066083,9965024,5563138,4985131,5036254,6272166,5610350,5324699,10533602,5097576,5448458,10853893,10351665,5126140,5635633,5061747,10181950,5645759,6092465,5703728,5068032,5211347,5193886,9900141,5498674,9857957,10524801,11053011,10606865,10116928,10100446,10521728,10334553,10557767,11081645,10580186,10469557,10147309,5045683,10382535,11119710,5538344,4825194,10795576,11084160,5088845,5388394,10596459,5734388,5541696,5547632,10103100,11051963,11268960,4928560,10359697,5205759,5651067,5481353,10198293,10221690,9948472,10550224,10144725,11203798,9975989,10214148,5268407,9966909,10828122,10722033,10343005,10667976,10427792,10065385,11299131,10372268,5096109,5415004,10195291,10226370,5799341,5036534,5481353,9934084,5458794,5523048,4925068,10184674,6015639,10797601,10153944,5564814,4979543,5794032,11662865,10302008,6090229,10212402,5186414,10279030,10445322,10572294,5737461,4936452,5286776,10214985,10171684,5255138,10208350,35686030,7560877,5184248,5590584,10054700,4870311,5330287,5087798,5144159,10170427,4989531,4924718,5247664,5236210,5059582,4812693,5688921,5655258,4868147,5183480,5263867,5352845,5312477,5270572,5154287,5166788,5245988,4904674,5356477,5062795,4931703,4960547,5047988,4770718,4849360,5033322,5013347,5544560,5222661,5107493,4939315,5113568,5270572,5251365,5598408,5032623,5719721,5174680,4813531,4770788,4986457,4979892,5365835,5563836,6130947,5609791,5341392,5700026,5745842,5719861,4919550,5104419,4875480,5332521,5622502,5270293,5321626,5479398,5171886,5222451,5052877,5144719,5697442,5231461,5426388,5839639,4876807,5558108,5411023,5481213,5427575,5095410,5611188,5224826,5060838,5221823,4932051,5215537,5702401,5597778,5668039,5287543,5201918,5397194,5406413,5312687,5726286,6030375,5160572,5056648,5097924,5424292,5263658,5182363,5195562,5275252,5995944,5412211,5052807,5653931,5681309,5659099,5212464,5316039,5719722,4854038,5180896,5480725,5259537,4923041,5177613,5169372,5597918,5178172,5302769,5684871,5412211,4794115,5551403,4909563,5267988,5153518,5129213,4828268,5129003,5145276,5014394,5085982,5644014,5241937,5195423,5035416,4991207,5193397,5257791,5423105,5399848,4768134,4981778,5047289,5807721,5054972,5372890,5582902,5780064,4888889,5300534,4955658,5104769,5479328,10367449,5016280,5099391,10021036,4817931,5232928]}